jsonconfigparser/utils.py
jsonconfigparser/__init__.py
jsonconfigparser/shell.py
jsonconfigparser/cli.py
jsonconfigparser/commands.py
jsonconfigparser/configparser.py
jsonconfigparser-0.1.2.dist-info/RECORD
jsonconfigparser-0.1.2.dist-info/WHEEL
jsonconfigparser-0.1.2.dist-info/METADATA
jsonconfigparser-0.1.2.dist-info/DESCRIPTION.rst
jsonconfigparser-0.1.2.dist-info/entry_points.txt
jsonconfigparser-0.1.2.dist-info/top_level.txt
jsonconfigparser-0.1.2.dist-info/metadata.json
