Metadata-Version: 2.0
Name: jsonconfigparser
Version: 0.1.2
Summary: Quick and easy editting of JSON files.
Home-page: https://github.com/justanr/JSONConfigParser
Author: Alec Nikolas Reiter
Author-email: alecreiter@gmail.com
License: MIT
Keywords: CLI json config
Platform: UNKNOWN
Classifier: Development Status :: 3 - Alpha
Classifier: Environment :: Console
Classifier: Intended Audience :: Developers
Classifier: License :: OSI Approved :: MIT License
Classifier: Topic :: Text Processing
Classifier: Programming Language :: Python :: 3.4
Classifier: Operating System :: POSIX :: Linux
Classifier: Natural Language :: English
Requires-Dist: decorator (==3.4.0)
Requires-Dist: jsonpath-rw (==1.3.0)
Requires-Dist: ply (==3.4)
Requires-Dist: six (==1.8.0)
